starred/__init__.py
starred/githubgql.py
starred/starred.py
starred-4.2.0.dist-info/LICENSE
starred-4.2.0.dist-info/METADATA
starred-4.2.0.dist-info/WHEEL
starred-4.2.0.dist-info/entry_points.txt
starred-4.2.0.dist-info/top_level.txt
starred-4.2.0.dist-info/RECORD
