Metadata-Version: 2.1
Name: starred
Version: 4.2.0
Summary: creating your own Awesome List used GitHub stars!
Home-page: https://github.com/maguowei/starred
Author: maguowei
Author-email: imaguowei@gmail.com
License: MIT
Keywords: GitHub starred
Platform: any
Classifier: Development Status :: 5 - Production/Stable
Classifier: Environment :: Web Environment
Classifier: Intended Audience :: Developers
Classifier: License :: OSI Approved :: MIT License
Classifier: Operating System :: OS Independent
Classifier: Programming Language :: Python
Classifier: Programming Language :: Python :: 3
Classifier: Programming Language :: Python :: 3.7
Classifier: Programming Language :: Python :: 3.8
Classifier: Programming Language :: Python :: 3.9
Classifier: Programming Language :: Python :: 3.10
Requires-Python: >=3.7
License-File: LICENSE
Requires-Dist: click (==8.1.3)
Requires-Dist: requests (==2.27.1)
Requires-Dist: github3.py (==3.2.0)
Requires-Dist: gql (==3.2.0)
Requires-Dist: aiohttp (==3.8.1)
